aeglos/__init__.py
aeglos/classes/GuardedAgentExecutor.py
aeglos/classes/GuardedChain.py
aeglos/classes/__init__.py
aeglos/classes/PromptChecker/PromptChecker.py
aeglos/classes/PromptChecker/__init__.py
aeglos/classes/PromptChecker/deny_list.py
aeglos/interfaces/GlobalMessages.py
aeglos/interfaces/__init__.py
aeglos-0.1.1.dist-info/LICENSE
aeglos-0.1.1.dist-info/METADATA
aeglos-0.1.1.dist-info/WHEEL
aeglos-0.1.1.dist-info/top_level.txt
aeglos-0.1.1.dist-info/RECORD
