Metadata-Version: 2.1
Name: aeglos
Version: 0.1.1
Summary: This package adds a SDK that guardrails your LLM applications from malicious prompts
Home-page: https://aeglos.ai/
Author: Alex, Anirudh
Author-email: alexandru@aeglos.ai, anirudh@aeglos.ai
Project-URL: Bug Tracker, https://github.com/anirudhramoo/prompInjection/issues
Classifier: Programming Language :: Python :: 3
Classifier: License :: OSI Approved :: MIT License
Classifier: Operating System :: OS Independent
Requires-Python: >=3.6
License-File: LICENSE
